{
    "partname": "optimization",
    "runtime": 186.79998240526766,
    "results": {
        "CONF2": {
            "xtb_opt": {
                "energy": -233.6080262,
                "grad_norm": 0.00041985853,
                "converged": true,
                "geom": [
                    {
                        "element": "C",
                        "xyz": [
                            -1.297527985687802,
                            -0.9317545568976014,
                            -0.17830389132803964
                        ]
                    },
                    {
                        "element": "C",
                        "xyz": [
                            -0.4218682904751591,
                            0.31173779148420655,
                            -0.3262175071110521
                        ]
                    },
                    {
                        "element": "C",
                        "xyz": [
                            -1.1146293760678052,
                            1.5399147788982457,
                            0.26492441897714153
                        ]
                    },
                    {
                        "element": "C",
                        "xyz": [
                            0.9318923355228015,
                            0.1296951151246014,
                            0.35526033602102625
                        ]
                    },
                    {
                        "element": "O",
                        "xyz": [
                            1.7196131194303634,
                            -0.9398852336825232,
                            -0.2023659606196539
                        ]
                    },
                    {
                        "element": "H",
                        "xyz": [
                            -1.4957775821445032,
                            -1.1383102298822216,
                            0.8808621355216522
                        ]
                    },
                    {
                        "element": "H",
                        "xyz": [
                            -0.8289073034964646,
                            -1.8193004897338882,
                            -0.6175401122920036
                        ]
                    },
                    {
                        "element": "H",
                        "xyz": [
                            -2.2605155437866755,
                            -0.7892220442296218,
                            -0.679525940462962
                        ]
                    },
                    {
                        "element": "H",
                        "xyz": [
                            -0.23561350710829035,
                            0.4906032741497332,
                            -1.394413987486339
                        ]
                    },
                    {
                        "element": "H",
                        "xyz": [
                            -0.5042032320133647,
                            2.4413677614624407,
                            0.1435285960745918
                        ]
                    },
                    {
                        "element": "H",
                        "xyz": [
                            -1.3016534254445027,
                            1.3991529837043546,
                            1.3363298622752864
                        ]
                    },
                    {
                        "element": "H",
                        "xyz": [
                            -2.0788988323244735,
                            1.716498261696789,
                            -0.2220142236110196
                        ]
                    },
                    {
                        "element": "H",
                        "xyz": [
                            1.5350288655511553,
                            1.035298692493311,
                            0.23043416056014504
                        ]
                    },
                    {
                        "element": "H",
                        "xyz": [
                            0.7843650295376509,
                            -0.03382814241784508,
                            1.4340068448995544
                        ]
                    },
                    {
                        "element": "H",
                        "xyz": [
                            1.296718257626494,
                            -1.7722760963675475,
                            0.04187088109024282
                        ]
                    }
                ],
                "cycles": 9,
                "ecyc": [
                    -233.6076536,
                    -233.607833,
                    -233.6079027,
                    -233.607948,
                    -233.6079825,
                    -233.6080081,
                    -233.6080194,
                    -233.6080227,
                    -233.6080262
                ],
                "gncyc": [
                    0.03052468193,
                    0.0113297,
                    0.0039122,
                    0.0034406,
                    0.0044122,
                    0.0041124,
                    0.0027355,
                    0.0010579,
                    0.0011663,
                    0.001175198004,
                    0.001167023785,
                    0.0003871,
                    0.00041985853
                ]
            },
            "xtb_rrho": {
                "energy": 0.104043291162,
                "rmsd": null,
                "gibbs": {
                    "298.15": 0.104043291162
                },
                "enthalpy": {
                    "298.15": null
                },
                "entropy": {
                    "298.15": null
                },
                "symmetry": "c1",
                "symnum": 1,
                "linear": false
            },
            "gtot": -233.50398290883803,
            "bmw": 0.3760936586639819
        },
        "CONF1": {
            "xtb_opt": {
                "energy": -233.607832,
                "grad_norm": 0.000674175288,
                "converged": true,
                "geom": [
                    {
                        "element": "C",
                        "xyz": [
                            -1.7396365210992124,
                            -0.8124954459857016,
                            0.003618767837171763
                        ]
                    },
                    {
                        "element": "C",
                        "xyz": [
                            -0.4925090897527733,
                            0.0037619342629756367,
                            -0.33747091516231026
                        ]
                    },
                    {
                        "element": "C",
                        "xyz": [
                            -0.6468290173464387,
                            1.4557080402401887,
                            0.11121086877031164
                        ]
                    },
                    {
                        "element": "C",
                        "xyz": [
                            0.7263406061149951,
                            -0.6552016240683979,
                            0.3022540455571569
                        ]
                    },
                    {
                        "element": "O",
                        "xyz": [
                            1.9673287523206366,
                            0.00038599499398532186,
                            -0.018651737305928767
                        ]
                    },
                    {
                        "element": "H",
                        "xyz": [
                            -1.6546438809451807,
                            -1.845263067227425,
                            -0.35173306379676406
                        ]
                    },
                    {
                        "element": "H",
                        "xyz": [
                            -2.630831393234055,
                            -0.37023192088535445,
                            -0.4530345276629744
                        ]
                    },
                    {
                        "element": "H",
                        "xyz": [
                            -1.8979749300018243,
                            -0.8393265685251098,
                            1.088712546953388
                        ]
                    },
                    {
                        "element": "H",
                        "xyz": [
                            -0.3470462056357201,
                            -0.018397547419342096,
                            -1.4279425842735531
                        ]
                    },
                    {
                        "element": "H",
                        "xyz": [
                            0.23356279561446947,
                            2.05320937423281,
                            -0.14286221195182114
                        ]
                    },
                    {
                        "element": "H",
                        "xyz": [
                            -0.7899050407692169,
                            1.5065573695478256,
                            1.1975058171707544
                        ]
                    },
                    {
                        "element": "H",
                        "xyz": [
                            -1.5165677506258493,
                            1.9199980329459863,
                            -0.3647835013399425
                        ]
                    },
                    {
                        "element": "H",
                        "xyz": [
                            0.641183513462983,
                            -0.6124123963465237,
                            1.3949093352716027
                        ]
                    },
                    {
                        "element": "H",
                        "xyz": [
                            0.7756725958673325,
                            -1.713798392179356,
                            0.007354049312004463
                        ]
                    },
                    {
                        "element": "H",
                        "xyz": [
                            2.071783385277922,
                            -0.04423650484997517,
                            -0.9779227542045223
                        ]
                    }
                ],
                "cycles": 8,
                "ecyc": [
                    -233.6075478,
                    -233.6077146,
                    -233.607754,
                    -233.6077789,
                    -233.6077973,
                    -233.6078189,
                    -233.6078287,
                    -233.607832
                ],
                "gncyc": [
                    0.030552058267,
                    0.0115252,
                    0.0040485,
                    0.0020442,
                    0.0020773,
                    0.0024016,
                    0.0026135,
                    0.0013673,
                    0.0006031,
                    0.000674175288
                ]
            },
            "xtb_rrho": {
                "energy": 0.104230089985,
                "rmsd": null,
                "gibbs": {
                    "298.15": 0.104230089985
                },
                "enthalpy": {
                    "298.15": null
                },
                "entropy": {
                    "298.15": null
                },
                "symmetry": "c1",
                "symnum": 1,
                "linear": false
            },
            "gtot": -233.503601910015,
            "bmw": 0.25121680215743764
        },
        "CONF4": {
            "xtb_opt": {
                "energy": -233.6074694,
                "grad_norm": 0.000689710945,
                "converged": true,
                "geom": [
                    {
                        "element": "C",
                        "xyz": [
                            -1.3705145822742648,
                            -0.8924395692637821,
                            0.3843104314957872
                        ]
                    },
                    {
                        "element": "C",
                        "xyz": [
                            -0.5831659790142766,
                            0.0777408184571127,
                            -0.4966242996019232
                        ]
                    },
                    {
                        "element": "C",
                        "xyz": [
                            -0.6985752232600704,
                            1.5126285331870704,
                            0.021187957036006767
                        ]
                    },
                    {
                        "element": "C",
                        "xyz": [
                            0.8767081611890973,
                            -0.34947581823952406,
                            -0.6445459754252318
                        ]
                    },
                    {
                        "element": "O",
                        "xyz": [
                            1.5977045214173433,
                            -0.38321496734363736,
                            0.6038682005444848
                        ]
                    },
                    {
                        "element": "H",
                        "xyz": [
                            -2.429127837565032,
                            -0.616488220527096,
                            0.4168294553874381
                        ]
                    },
                    {
                        "element": "H",
                        "xyz": [
                            -0.9927796555182395,
                            -0.8813017972323662,
                            1.4121849452433812
                        ]
                    },
                    {
                        "element": "H",
                        "xyz": [
                            -1.2991743378629173,
                            -1.9186804866083724,
                            0.0085343467856395
                        ]
                    },
                    {
                        "element": "H",
                        "xyz": [
                            -1.0008342034815176,
                            0.043570535778057355,
                            -1.5131041283958955
                        ]
                    },
                    {
                        "element": "H",
                        "xyz": [
                            -1.7439602965015135,
                            1.8374448627608067,
                            0.03145936332974548
                        ]
                    },
                    {
                        "element": "H",
                        "xyz": [
                            -0.13291577719071723,
                            2.2111589213057576,
                            -0.6054677149831169
                        ]
                    },
                    {
                        "element": "H",
                        "xyz": [
                            -0.32312527516701084,
                            1.5939385797780776,
                            1.048509306492761
                        ]
                    },
                    {
                        "element": "H",
                        "xyz": [
                            0.9285539509016428,
                            -1.369556671757331,
                            -1.0398040706449292
                        ]
                    },
                    {
                        "element": "H",
                        "xyz": [
                            1.3902225046680439,
                            0.3169127756670657,
                            -1.3527477606502234
                        ]
                    },
                    {
                        "element": "H",
                        "xyz": [
                            1.6676965104259176,
                            0.5252304541012073,
                            0.9229139730459005
                        ]
                    }
                ],
                "cycles": 8,
                "ecyc": [
                    -233.6071536,
                    -233.607341,
                    -233.6073882,
                    -233.6074198,
                    -233.6074408,
                    -233.6074595,
                    -233.6074668,
                    -233.6074694
                ],
                "gncyc": [
                    0.032044153303,
                    0.0124292,
                    0.0042953,
                    0.0022141,
                    0.0024767,
                    0.0025419,
                    0.0018466,
                    0.0004966,
                    0.000639,
                    0.000689710945
                ]
            },
            "xtb_rrho": {
                "energy": 0.104384146619,
                "rmsd": null,
                "gibbs": {
                    "298.15": 0.104384146619
                },
                "enthalpy": {
                    "298.15": null
                },
                "entropy": {
                    "298.15": null
                },
                "symmetry": "c1",
                "symnum": 1,
                "linear": false
            },
            "gtot": -233.50308525338102,
            "bmw": 0.14534599904473625
        },
        "CONF3": {
            "xtb_opt": {
                "energy": -233.6070624,
                "grad_norm": 0.000266689979,
                "converged": true,
                "geom": [
                    {
                        "element": "C",
                        "xyz": [
                            -1.2708711563851822,
                            -0.9504230830637639,
                            -0.18193317021819544
                        ]
                    },
                    {
                        "element": "C",
                        "xyz": [
                            -0.4019120179004052,
                            0.2997553826833312,
                            -0.3156043380376971
                        ]
                    },
                    {
                        "element": "C",
                        "xyz": [
                            -1.1257035745356176,
                            1.5289871991648771,
                            0.23476304853952787
                        ]
                    },
                    {
                        "element": "C",
                        "xyz": [
                            0.926022518166838,
                            0.13955092745269618,
                            0.4082591424807431
                        ]
                    },
                    {
                        "element": "O",
                        "xyz": [
                            1.6631816444753964,
                            -0.9525825363811229,
                            -0.1773724929792744
                        ]
                    },
                    {
                        "element": "H",
                        "xyz": [
                            -0.7780198750941597,
                            -1.8350167061439908,
                            -0.5953212444396698
                        ]
                    },
                    {
                        "element": "H",
                        "xyz": [
                            -2.2214060379957585,
                            -0.818681489100329,
                            -0.7092328689314877
                        ]
                    },
                    {
                        "element": "H",
                        "xyz": [
                            -1.4953873582113173,
                            -1.1480242955390492,
                            0.8735299755308106
                        ]
                    },
                    {
                        "element": "H",
                        "xyz": [
                            -0.18318527179587604,
                            0.4687392863890359,
                            -1.3795493710033424
                        ]
                    },
                    {
                        "element": "H",
                        "xyz": [
                            -1.334901188342128,
                            1.407961524043028,
                            1.3044892117041342
                        ]
                    },
                    {
                        "element": "H",
                        "xyz": [
                            -2.0813190491569533,
                            1.677129308100391,
                            -0.2777611000520105
                        ]
                    },
                    {
                        "element": "H",
                        "xyz": [
                            -0.5283844775625783,
                            2.438076818463554,
                            0.10696040496900074
                        ]
                    },
                    {
                        "element": "H",
                        "xyz": [
                            1.5087060471285603,
                            1.0684523435073918,
                            0.32726228232950955
                        ]
                    },
                    {
                        "element": "H",
                        "xyz": [
                            0.7422029293926645,
                            -0.058806197825802334,
                            1.475536613056904
                        ]
                    },
                    {
                        "element": "H",
                        "xyz": [
                            2.4863158636516944,
                            -1.0414813089470416,
                            0.31814740623873905
                        ]
                    }
                ],
                "cycles": 8,
                "ecyc": [
                    -233.6067819,
                    -233.6069592,
                    -233.6069979,
                    -233.6070218,
                    -233.607038,
                    -233.6070507,
                    -233.6070609,
                    -233.6070624
                ],
                "gncyc": [
                    0.029788239392,
                    0.0117642,
                    0.0040499,
                    0.0021398,
                    0.0018535,
                    0.002405,
                    0.0018966,
                    0.000742,
                    0.0002828,
                    0.000266689979
                ]
            },
            "xtb_rrho": {
                "energy": 0.103880161795,
                "rmsd": null,
                "gibbs": {
                    "298.15": 0.103880161795
                },
                "enthalpy": {
                    "298.15": null
                },
                "entropy": {
                    "298.15": null
                },
                "symmetry": "c1",
                "symnum": 1,
                "linear": false
            },
            "gtot": -233.503182238205,
            "bmw": 0.16106938946684363
        },
        "CONF5": {
            "xtb_opt": {
                "energy": -233.6063383,
                "grad_norm": 0.000333061403,
                "converged": true,
                "geom": [
                    {
                        "element": "C",
                        "xyz": [
                            -1.3546072061368433,
                            -0.8718200222487247,
                            0.4210526501259807
                        ]
                    },
                    {
                        "element": "C",
                        "xyz": [
                            -0.5763853913980442,
                            0.0841403089132655,
                            -0.48514621974366595
                        ]
                    },
                    {
                        "element": "C",
                        "xyz": [
                            -0.6690669020541917,
                            1.5243349870001117,
                            0.0225544577332252
                        ]
                    },
                    {
                        "element": "C",
                        "xyz": [
                            0.8684876510753493,
                            -0.35927172903746846,
                            -0.6679286973111531
                        ]
                    },
                    {
                        "element": "O",
                        "xyz": [
                            1.5462410871208214,
                            -0.337772243868311,
                            0.6065136157644383
                        ]
                    },
                    {
                        "element": "H",
                        "xyz": [
                            -1.2860257005597735,
                            -1.9046611240543614,
                            0.06227736383724264
                        ]
                    },
                    {
                        "element": "H",
                        "xyz": [
                            -2.413259518721636,
                            -0.5950217351491673,
                            0.45524560631696076
                        ]
                    },
                    {
                        "element": "H",
                        "xyz": [
                            -0.9705573391886888,
                            -0.8421639612793117,
                            1.4461478873729243
                        ]
                    },
                    {
                        "element": "H",
                        "xyz": [
                            -1.0195011340377291,
                            0.04383801960443857,
                            -1.4899277275375813
                        ]
                    },
                    {
                        "element": "H",
                        "xyz": [
                            -0.11026429622089703,
                            2.2106195359190033,
                            -0.623146403387838
                        ]
                    },
                    {
                        "element": "H",
                        "xyz": [
                            -0.2675268302006772,
                            1.6100864115415652,
                            1.0377176487134894
                        ]
                    },
                    {
                        "element": "H",
                        "xyz": [
                            -1.7116252778109684,
                            1.8573750895085241,
                            0.04881835006253596
                        ]
                    },
                    {
                        "element": "H",
                        "xyz": [
                            0.8949775422380606,
                            -1.3757983148446609,
                            -1.0865049095068988
                        ]
                    },
                    {
                        "element": "H",
                        "xyz": [
                            1.3776281741709333,
                            0.3155244724157232,
                            -1.371225831651586
                        ]
                    },
                    {
                        "element": "H",
                        "xyz": [
                            2.4567169104822986,
                            -0.6160975837411323,
                            0.4512108434031958
                        ]
                    }
                ],
                "cycles": 7,
                "ecyc": [
                    -233.6059282,
                    -233.606204,
                    -233.6062625,
                    -233.6063026,
                    -233.6063215,
                    -233.6063352,
                    -233.6063383
                ],
                "gncyc": [
                    0.030944415401,
                    0.0127048,
                    0.0045311,
                    0.0025937,
                    0.0020232,
                    0.0020485,
                    0.0013928,
                    0.00028,
                    0.000333061403
                ]
            },
            "xtb_rrho": {
                "energy": 0.103994530356,
                "rmsd": null,
                "gibbs": {
                    "298.15": 0.103994530356
                },
                "enthalpy": {
                    "298.15": null
                },
                "entropy": {
                    "298.15": null
                },
                "symmetry": "c1",
                "symnum": 1,
                "linear": false
            },
            "gtot": -233.502343769644,
            "bmw": 0.06627415066700047
        }
    },
    "settings": {
        "optcycles": 8,
        "maxcyc": 200,
        "threshold": 1.5,
        "hlow": 0.01,
        "gradthr": 0.01,
        "func": "r2scan-3c",
        "basis": "def2-tzvp",
        "prog": "orca",
        "sm": "smd",
        "gfnv": "gfn2",
        "optlevel": "normal",
        "run": true,
        "macrocycles": true,
        "crestcheck": true,
        "template": false,
        "constrain": false,
        "xtb_opt": true
    },
    "nconf_in": 5,
    "nconf_out": 5
}