{
    "partname": "optimization",
    "runtime": 105.50132992491126,
    "results": {
        "CONF1": {
            "xtb_opt": {
                "energy": -713.3094794,
                "cycles": 4,
                "converged": true,
                "ecyc": [
                    -713.3093333,
                    -713.3094637,
                    -713.3094758,
                    -713.3094794
                ],
                "grad_norm": 0.000918986439,
                "gncyc": [
                    0.028453478829,
                    0.0118707,
                    0.0038335,
                    0.0015354,
                    0.0009307,
                    0.000918986439
                ],
                "geom": [
                    {
                        "element": "C",
                        "xyz": [
                            0.25543131962584065,
                            -0.535837528550344,
                            0.0006473889570392679
                        ]
                    },
                    {
                        "element": "C",
                        "xyz": [
                            1.3922494122222917,
                            0.15200628839495842,
                            -0.0009174121988708722
                        ]
                    },
                    {
                        "element": "F",
                        "xyz": [
                            2.582928155947811,
                            -0.3935507971202236,
                            -0.001027258321482798
                        ]
                    },
                    {
                        "element": "F",
                        "xyz": [
                            1.4318534725300192,
                            1.4658358535372997,
                            -0.002988814382958079
                        ]
                    },
                    {
                        "element": "C",
                        "xyz": [
                            -1.1010819797381188,
                            0.11063783809007607,
                            0.0002551962071240159
                        ]
                    },
                    {
                        "element": "F",
                        "xyz": [
                            -1.2952015996418,
                            0.8883267940315631,
                            1.0918410804559495
                        ]
                    },
                    {
                        "element": "F",
                        "xyz": [
                            -1.2816565093357228,
                            0.9123589057345103,
                            -1.0758892164096676
                        ]
                    },
                    {
                        "element": "F",
                        "xyz": [
                            -2.0598845543406967,
                            -0.8285575446869017,
                            -0.015789802801372068
                        ]
                    },
                    {
                        "element": "F",
                        "xyz": [
                            0.27947614784989433,
                            -1.8768683346930164,
                            0.003814038269695735
                        ]
                    }
                ]
            },
            "xtb_rrho": {
                "energy": -0.004136388934,
                "rmsd": null,
                "gibbs": {
                    "298.15": -0.004136388934
                },
                "enthalpy": {
                    "298.15": null
                },
                "entropy": {
                    "298.15": null
                },
                "symmetry": "c1",
                "symnum": 1,
                "linear": false
            },
            "gtot": -713.3136157889339,
            "bmw": 1.0
        }
    },
    "settings": {
        "optcycles": 8,
        "maxcyc": 200,
        "threshold": 1.5,
        "hlow": 0.01,
        "gradthr": 0.01,
        "func": "r2scan-3c",
        "basis": "def2-tzvp",
        "prog": "orca",
        "sm": "smd",
        "gfnv": "gfn2",
        "optlevel": "normal",
        "run": true,
        "macrocycles": false,
        "crestcheck": true,
        "template": false,
        "constrain": false,
        "xtb_opt": true
    },
    "nconf_in": 1,
    "nconf_out": 1
}