{
    "partname": "screening",
    "runtime": 42.85681603476405,
    "results": {
        "CONF1": {
            "gsolv": {
                "gsolv": -0.006946246870029427,
                "energy_gas": -287.516991499339,
                "energy_solv": -287.523937746209
            },
            "gtot": -287.523937746209,
            "bmw": 1.0
        }
    },
    "settings": {
        "threshold": 3.5,
        "func": "r2scan-3c",
        "basis": "def2-tzvp",
        "prog": "orca",
        "sm": "smd",
        "gfnv": "gfn2",
        "run": true,
        "implicit": false,
        "template": false
    },
    "nconf_in": 1,
    "nconf_out": 1
}