{
    "partname": "screening",
    "runtime": 53.61730346083641,
    "results": {
        "CONF1": {
            "gsolv": {
                "gsolv": -0.0047439878509862865,
                "energy_gas": -436.671597616811,
                "energy_solv": -436.676341604662
            },
            "gtot": -436.676341604662,
            "bmw": 1.0
        }
    },
    "settings": {
        "threshold": 3.5,
        "func": "r2scan-3c",
        "basis": "def2-tzvp",
        "prog": "orca",
        "sm": "smd",
        "gfnv": "gfn2",
        "run": true,
        "implicit": false,
        "template": false
    },
    "nconf_in": 1,
    "nconf_out": 1
}