{
    "partname": "optimization",
    "runtime": 147.68204129580408,
    "results": {
        "CONF1": {
            "xtb_opt": {
                "energy": -233.5902872,
                "grad_norm": 0.000597318659,
                "converged": true,
                "geom": [
                    {
                        "element": "C",
                        "xyz": [
                            0.6896590927134453,
                            -1.4282516759196129,
                            -0.10026030012485963
                        ]
                    },
                    {
                        "element": "C",
                        "xyz": [
                            0.4495226380693265,
                            0.01053491980774559,
                            0.33568268004096363
                        ]
                    },
                    {
                        "element": "C",
                        "xyz": [
                            1.618782211537863,
                            0.9102459040332598,
                            -0.01747528317010981
                        ]
                    },
                    {
                        "element": "O",
                        "xyz": [
                            -0.7095538665572485,
                            0.5842167310869288,
                            -0.31127505991402826
                        ]
                    },
                    {
                        "element": "C",
                        "xyz": [
                            -1.9422068187436223,
                            0.002162508103633241,
                            0.10943312166859546
                        ]
                    },
                    {
                        "element": "H",
                        "xyz": [
                            0.8285790642876059,
                            -1.4787876049481876,
                            -1.1860669158164838
                        ]
                    },
                    {
                        "element": "H",
                        "xyz": [
                            1.5950743163797718,
                            -1.8108248151840383,
                            0.3810377901283606
                        ]
                    },
                    {
                        "element": "H",
                        "xyz": [
                            -0.13702854846208704,
                            -2.086602708581697,
                            0.18022184301958008
                        ]
                    },
                    {
                        "element": "H",
                        "xyz": [
                            0.27654311078214083,
                            0.038242057137703865,
                            1.4240245920125971
                        ]
                    },
                    {
                        "element": "H",
                        "xyz": [
                            2.5275022507646807,
                            0.5575290420848299,
                            0.47842639575482554
                        ]
                    },
                    {
                        "element": "H",
                        "xyz": [
                            1.4289879932119418,
                            1.9398413517152948,
                            0.300264565463919
                        ]
                    },
                    {
                        "element": "H",
                        "xyz": [
                            1.792425102990354,
                            0.9029083489795978,
                            -1.0991803328706662
                        ]
                    },
                    {
                        "element": "H",
                        "xyz": [
                            -2.0633328269681237,
                            -1.025899519741256,
                            -0.2564501519434092
                        ]
                    },
                    {
                        "element": "H",
                        "xyz": [
                            -2.7446204488848434,
                            0.6164580391254305,
                            -0.3077147475985016
                        ]
                    },
                    {
                        "element": "H",
                        "xyz": [
                            -2.02595672299944,
                            0.001982963970348954,
                            1.206179355838898
                        ]
                    }
                ],
                "cycles": 8,
                "ecyc": [
                    -233.5900402,
                    -233.5902156,
                    -233.5902497,
                    -233.5902644,
                    -233.5902715,
                    -233.5902799,
                    -233.5902847,
                    -233.5902872
                ],
                "gncyc": [
                    0.029066995812,
                    0.0110435,
                    0.0043967,
                    0.0021921,
                    0.0011672,
                    0.0011303,
                    0.0009924,
                    0.0010439,
                    0.0006073,
                    0.000597318659
                ]
            },
            "xtb_rrho": {
                "energy": 0.102688570468,
                "rmsd": null,
                "gibbs": {
                    "298.15": 0.102688570468
                },
                "enthalpy": {
                    "298.15": null
                },
                "entropy": {
                    "298.15": null
                },
                "symmetry": "c1",
                "symnum": 1,
                "linear": false
            },
            "gtot": -233.48759862953202,
            "bmw": 0.9421483847539895
        },
        "CONF2": {
            "xtb_opt": {
                "energy": -233.5881461,
                "grad_norm": 0.00079541361,
                "converged": true,
                "geom": [
                    {
                        "element": "C",
                        "xyz": [
                            0.7173170117179875,
                            -1.4846477068469623,
                            -0.07320913876835078
                        ]
                    },
                    {
                        "element": "C",
                        "xyz": [
                            0.5461901164037454,
                            -0.07205925515629903,
                            0.4678109583039886
                        ]
                    },
                    {
                        "element": "C",
                        "xyz": [
                            1.2946036817415296,
                            0.9584420130849958,
                            -0.3664775063519939
                        ]
                    },
                    {
                        "element": "O",
                        "xyz": [
                            -0.8505904404262739,
                            0.27943685876271407,
                            0.6460051660957752
                        ]
                    },
                    {
                        "element": "C",
                        "xyz": [
                            -1.6242416997910298,
                            0.31496301185358333,
                            -0.5546422268286094
                        ]
                    },
                    {
                        "element": "H",
                        "xyz": [
                            0.11485715359946413,
                            -2.197231612908339,
                            0.49897925089315426
                        ]
                    },
                    {
                        "element": "H",
                        "xyz": [
                            0.43972798595083723,
                            -1.5533759366480582,
                            -1.1296305897630605
                        ]
                    },
                    {
                        "element": "H",
                        "xyz": [
                            1.767664388826494,
                            -1.7798945661999852,
                            0.013660237607815238
                        ]
                    },
                    {
                        "element": "H",
                        "xyz": [
                            0.932107091548737,
                            -0.0401874458615801,
                            1.4932682826350723
                        ]
                    },
                    {
                        "element": "H",
                        "xyz": [
                            1.0194583041917376,
                            0.9042284305052717,
                            -1.4243600012430995
                        ]
                    },
                    {
                        "element": "H",
                        "xyz": [
                            2.3703220008271466,
                            0.7703664060821007,
                            -0.2935254358840733
                        ]
                    },
                    {
                        "element": "H",
                        "xyz": [
                            1.099979427309885,
                            1.971714063240801,
                            -0.0009789248782501858
                        ]
                    },
                    {
                        "element": "H",
                        "xyz": [
                            -1.2531477617573308,
                            1.0657976364084176,
                            -1.2638187181116778
                        ]
                    },
                    {
                        "element": "H",
                        "xyz": [
                            -2.6398975732357624,
                            0.5892033116408263,
                            -0.258810812853968
                        ]
                    },
                    {
                        "element": "H",
                        "xyz": [
                            -1.6583966188514376,
                            -0.6624071774494101,
                            -1.0525403440878385
                        ]
                    }
                ],
                "cycles": 5,
                "ecyc": [
                    -233.5879543,
                    -233.5880991,
                    -233.588129,
                    -233.588142,
                    -233.5881461
                ],
                "gncyc": [
                    0.026205906011,
                    0.0107448,
                    0.0040662,
                    0.002032,
                    0.000973,
                    0.0007613,
                    0.00079541361
                ]
            },
            "xtb_rrho": {
                "energy": 0.103182008948,
                "rmsd": null,
                "gibbs": {
                    "298.15": 0.103182008948
                },
                "enthalpy": {
                    "298.15": null
                },
                "entropy": {
                    "298.15": null
                },
                "symmetry": "c1",
                "symnum": 1,
                "linear": false
            },
            "gtot": -233.48496409105198,
            "bmw": 0.05785161524601049
        }
    },
    "settings": {
        "optcycles": 8,
        "maxcyc": 200,
        "threshold": 1.5,
        "hlow": 0.01,
        "gradthr": 0.01,
        "func": "r2scan-3c",
        "basis": "def2-tzvp",
        "prog": "orca",
        "sm": "smd",
        "gfnv": "gfn2",
        "optlevel": "normal",
        "run": true,
        "macrocycles": true,
        "crestcheck": true,
        "template": false,
        "constrain": false,
        "xtb_opt": true
    },
    "nconf_in": 2,
    "nconf_out": 2
}